weppy/__init__.py
weppy/_compat.py
weppy/_internal.py
weppy/_reloader.py
weppy/app.py
weppy/cache.py
weppy/cli.py
weppy/datastructures.py
weppy/debug.py
weppy/expose.py
weppy/extensions.py
weppy/forms.py
weppy/globals.py
weppy/helpers.py
weppy/html.py
weppy/http.py
weppy/logger.py
weppy/pipeline.py
weppy/security.py
weppy/serializers.py
weppy/sessions.py
weppy/stream.py
weppy/utils.py
weppy/wsgi.py
weppy/assets/helpers.js
weppy/assets/jquery.min.js
weppy/assets/jquery.min.map
weppy/assets/debug/shBrushPython.js
weppy/assets/debug/shCore.css
weppy/assets/debug/shCore.js
weppy/assets/debug/shTheme.css
weppy/assets/debug/view.css
weppy/assets/debug/view.html
weppy/language/__init__.py
weppy/language/cache.py
weppy/language/helpers.py
weppy/language/translator.py
weppy/language/plurals/__init__.py
weppy/language/plurals/af.py
weppy/language/plurals/bg.py
weppy/language/plurals/cs.py
weppy/language/plurals/de.py
weppy/language/plurals/en.py
weppy/language/plurals/es.py
weppy/language/plurals/fr.py
weppy/language/plurals/he.py
weppy/language/plurals/hi.py
weppy/language/plurals/hu.py
weppy/language/plurals/it.py
weppy/language/plurals/ja.py
weppy/language/plurals/lt.py
weppy/language/plurals/pl.py
weppy/language/plurals/pt.py
weppy/language/plurals/ro.py
weppy/language/plurals/ru.py
weppy/language/plurals/sk.py
weppy/language/plurals/sl.py
weppy/language/plurals/tr.py
weppy/language/plurals/uk.py
weppy/language/plurals/zh.py
weppy/libs/__init__.py
weppy/libs/contenttype.py
weppy/libs/pbkdf2.py
weppy/libs/portalocker.py
weppy/libs/rocket.py
weppy/libs/sanitizer.py
weppy/orm/__init__.py
weppy/orm/adapters.py
weppy/orm/apis.py
weppy/orm/base.py
weppy/orm/connection.py
weppy/orm/helpers.py
weppy/orm/models.py
weppy/orm/objects.py
weppy/orm/transactions.py
weppy/orm/wrappers.py
weppy/orm/migrations/__init__.py
weppy/orm/migrations/base.py
weppy/orm/migrations/commands.py
weppy/orm/migrations/engine.py
weppy/orm/migrations/exceptions.py
weppy/orm/migrations/generation.py
weppy-1.3.5.dist-info/LICENSE
weppy-1.3.5.dist-info/METADATA
weppy-1.3.5.dist-info/WHEEL
weppy-1.3.5.dist-info/entry_points.txt
weppy-1.3.5.dist-info/top_level.txt
weppy-1.3.5.dist-info/RECORD
